cython_npm/__init__.py
cython_npm/cythoncompile.py
cython_npm/go.py
cython_npm/install.py
cython_npm/typecheck.py
cython_npm-0.2.4.dist-info/DESCRIPTION.rst
cython_npm-0.2.4.dist-info/METADATA
cython_npm-0.2.4.dist-info/RECORD
cython_npm-0.2.4.dist-info/WHEEL
cython_npm-0.2.4.dist-info/metadata.json
cython_npm-0.2.4.dist-info/top_level.txt
