Metadata-Version: 1.1
Name: cython_npm
Version: 0.2.4
Summary: Cython project management like npm in nodejs
Home-page: https://github.com/minhtuan221/cython-npm
Author: Minh Tuan Nguyen
Author-email: ntuan221@gmail.com
License: MIT
Platform: POSIX
Classifier: Development Status :: 3 - Alpha
Classifier: License :: OSI Approved :: MIT License
Classifier: Environment :: Console
Classifier: Operating System :: POSIX
Classifier: Programming Language :: Python
Classifier: Programming Language :: Python :: 3.3
Classifier: Programming Language :: Python :: 3.4
Classifier: Programming Language :: Python :: 3.5
Classifier: Programming Language :: Python :: 3.6
